greenstalk/__init__.py
greenstalk/py.typed
greenstalk-2.1.0.dist-info/METADATA
greenstalk-2.1.0.dist-info/WHEEL
greenstalk-2.1.0.dist-info/licenses/LICENSE
greenstalk-2.1.0.dist-info/RECORD
