Metadata-Version: 2.4
Name: greenstalk
Version: 2.1.0
Summary: A Python client for the beanstalkd work queue
Project-URL: Documentation, https://greenstalk.readthedocs.io/
Project-URL: Source, https://github.com/justinmayhew/greenstalk
Author-email: Justin Mayhew <mayhew@live.ca>
License-Expression: MIT
License-File: LICENSE
Classifier: Intended Audience :: Developers
Classifier: Operating System :: OS Independent
Requires-Python: >=3.8
